py_to_proto/__init__.py
py_to_proto/compat.py
py_to_proto/compat_annotated.py
py_to_proto/converter_base.py
py_to_proto/dataclass_to_proto.py
py_to_proto/descriptor_to_file.py
py_to_proto/descriptor_to_message_class.py
py_to_proto/json_to_service.py
py_to_proto/jtd_to_proto.py
py_to_proto/utils.py
py_to_proto/validation.py
py_to_proto-0.6.0.dist-info/LICENSE
py_to_proto-0.6.0.dist-info/METADATA
py_to_proto-0.6.0.dist-info/WHEEL
py_to_proto-0.6.0.dist-info/top_level.txt
py_to_proto-0.6.0.dist-info/RECORD
